README.rst
setup.py
picup/__init__.py
picup/globals.py
picup/main_window.py
picup/upload.py
picup.egg-info/PKG-INFO
picup.egg-info/SOURCES.txt
picup.egg-info/dependency_links.txt
picup.egg-info/entry_points.txt
picup.egg-info/requires.txt
picup.egg-info/top_level.txt
picup/dialogs/__init__.py
picup/dialogs/key_request.py
picup/dialogs/show_links.py
picup/dialogs/url_input.py
picup/functions/__init__.py
picup/functions/api_key.py
picup/functions/load_ui.py
picup/functions/misc.py
picup/ui_files/KeyRequest.ui
picup/ui_files/LinkDialog.ui
picup/ui_files/LinkWidget.ui
picup/ui_files/MainWindow.ui
picup/ui_files/link_input.ui
picuplib/__init__.py
picuplib/checks.py
picuplib/exceptions.py
picuplib/globals.py
picuplib/misc.py
picuplib/upload.py