Metadata-Version: 1.1
Name: picup
Version: 0.5.1
Summary: PyQt based Picflash upload tool
Home-page: https://github.com/Arvedui/picup
Author: Arvedui
Author-email: Arvedui@posteo.de
License: GPLv2
Platform: UNKNOWN
Classifier: Development Status :: 4 - Beta
Classifier: Topic :: Software Development :: Libraries
Classifier: Intended Audience :: End Users/Desktop
Classifier: Operating System :: MacOS :: MacOS X
Classifier: Operating System :: Microsoft :: Windows
Classifier: Operating System :: POSIX
Classifier: License :: OSI Approved :: GNU General Public License v2 (GPLv2)
Classifier: Programming Language :: Python :: 3
Classifier: Environment :: X11 Applications :: Qt
